cli.py
cmcaine_cli-0.0.2.dist-info/LICENSE.txt
cmcaine_cli-0.0.2.dist-info/METADATA
cmcaine_cli-0.0.2.dist-info/WHEEL
cmcaine_cli-0.0.2.dist-info/top_level.txt
cmcaine_cli-0.0.2.dist-info/RECORD
