Metadata-Version: 2.1
Name: cmcaine-cli
Version: 0.0.2
Summary: Easy CLIs from function inspection
Home-page: https://github.com/cmcaine/cli
Author: Colin Caine
License: UNKNOWN
Platform: UNKNOWN
Classifier: Programming Language :: Python :: 3
Classifier: Operating System :: OS Independent
Classifier: License :: OSI Approved :: MIT License
